omaster/__init__.py
omaster/__main__.py
omaster/main.py
omaster/commands/__init__.py
omaster/commands/release_steps/__init__.py
omaster/commands/release_steps/step_1_validate.py
omaster/commands/release_steps/step_2_validate_code_quality.py
omaster/commands/release_steps/step_3_clean_build.py
omaster/commands/release_steps/step_4_analyze_changes.py
omaster/commands/release_steps/step_5_bump_version.py
omaster/commands/release_steps/step_5_publish.py
omaster/commands/release_steps/step_6_git_commit.py
omaster/core/__init__.py
omaster/core/config.py
omaster/core/errors.py
omaster/ui/__init__.py
omaster/ui/layout.py
omaster/utils/__init__.py
omaster/utils/version.py
omaster/validators/__init__.py
omaster-0.16.0.dist-info/METADATA
omaster-0.16.0.dist-info/WHEEL
omaster-0.16.0.dist-info/entry_points.txt
omaster-0.16.0.dist-info/RECORD
