Metadata-Version: 2.4
Name: omaster
Version: 0.16.0
Summary: A Python package release tool that automates the entire release process with built-in quality checks and AI-powered features.
Requires-Python: >=3.9
Requires-Dist: openai>=1.0.0
Requires-Dist: radon>=6.0.0
Requires-Dist: rich>=10.0.0
Requires-Dist: tomli>=2.0.0
Requires-Dist: vulture>=2.10.0
